flask_tools/__init__.py
flask_tools-0.1.0.dist-info/METADATA
flask_tools-0.1.0.dist-info/RECORD
flask_tools-0.1.0.dist-info/WHEEL
flask_tools-0.1.0.dist-info/top_level.txt
