Metadata-Version: 2.1
Name: flask-tools
Version: 0.1.0
Summary: Tools for Flask application.
Home-page: https://github.com/qileroro/flask-tools/
Author: qileroro
Author-email: qileroro@qq.com
License: Apache License, Version 2.0
Platform: UNKNOWN
Classifier: Development Status :: 3 - Alpha
Classifier: License :: OSI Approved :: Apache Software License
Classifier: Programming Language :: Python :: 2
Classifier: Programming Language :: Python :: 2.7
Requires-Dist: flask
Requires-Dist: commony
